Metadata-Version: 1.0
Name: weworkapi
Version: 0.1.7
Summary: weworkapi修改了wework包中的WXBizMsgCrypt.py文件，修改结果另存为WXBizMsgCrypt3.py文件
Home-page: UNKNOWN
Author: may.xiaoya.zhang
Author-email: may.xiaoya.zhang@gmail.com
License: UNKNOWN
Platform: UNKNOWN
